XiandaiJavascriptJiaocheng/README.md
XiandaiJavascriptJiaocheng/__init__.py
XiandaiJavascriptJiaocheng/__main__.py
XiandaiJavascriptJiaocheng/file.epub
XiandaiJavascriptJiaocheng/index.html
XiandaiJavascriptJiaocheng/css/__init__.py
XiandaiJavascriptJiaocheng/css/annotations.css
XiandaiJavascriptJiaocheng/css/main.css
XiandaiJavascriptJiaocheng/css/normalize.css
XiandaiJavascriptJiaocheng/css/popup.css
XiandaiJavascriptJiaocheng/font/__init__.py
XiandaiJavascriptJiaocheng/font/fontello.eot
XiandaiJavascriptJiaocheng/font/fontello.svg
XiandaiJavascriptJiaocheng/font/fontello.ttf
XiandaiJavascriptJiaocheng/font/fontello.woff
XiandaiJavascriptJiaocheng/img/__init__.py
XiandaiJavascriptJiaocheng/img/annotator-glyph-sprite.png
XiandaiJavascriptJiaocheng/img/annotator-icon-sprite.png
XiandaiJavascriptJiaocheng/img/apple-touch-icon.png
XiandaiJavascriptJiaocheng/img/cancelfullscreen.png
XiandaiJavascriptJiaocheng/img/close.png
XiandaiJavascriptJiaocheng/img/fullscreen.png
XiandaiJavascriptJiaocheng/img/loader.gif
XiandaiJavascriptJiaocheng/img/menu-icon.png
XiandaiJavascriptJiaocheng/img/save.png
XiandaiJavascriptJiaocheng/img/saved.png
XiandaiJavascriptJiaocheng/img/settings-s.png
XiandaiJavascriptJiaocheng/img/settings.png
XiandaiJavascriptJiaocheng/img/star.png
XiandaiJavascriptJiaocheng/js/__init__.py
XiandaiJavascriptJiaocheng/js/epub.js
XiandaiJavascriptJiaocheng/js/epub.min.js
XiandaiJavascriptJiaocheng/js/epub.min.map
XiandaiJavascriptJiaocheng/js/hooks.min.js
XiandaiJavascriptJiaocheng/js/hooks.min.map
XiandaiJavascriptJiaocheng/js/reader.js
XiandaiJavascriptJiaocheng/js/reader.js.map
XiandaiJavascriptJiaocheng/js/reader.min.js
XiandaiJavascriptJiaocheng/js/reader.min.map
XiandaiJavascriptJiaocheng/js/hooks/__init__.py
XiandaiJavascriptJiaocheng/js/hooks/extensions/__init__.py
XiandaiJavascriptJiaocheng/js/hooks/extensions/highlight.js
XiandaiJavascriptJiaocheng/js/libs/__init__.py
XiandaiJavascriptJiaocheng/js/libs/jquery.min.js
xiandai_javascript_jiaocheng-2024.3.5.0.dist-info/METADATA
xiandai_javascript_jiaocheng-2024.3.5.0.dist-info/WHEEL
xiandai_javascript_jiaocheng-2024.3.5.0.dist-info/entry_points.txt
xiandai_javascript_jiaocheng-2024.3.5.0.dist-info/top_level.txt
xiandai_javascript_jiaocheng-2024.3.5.0.dist-info/RECORD
